{
    "/ExamDetail.js": "/ExamDetail.js",
    "/ContestDetail.js": "/ContestDetail.js",
    "/ProblemDetail.js": "/ProblemDetail.js",
    "/ExamProblem.js": "/ExamProblem.js",
    "/ContestProblem.js": "/ContestProblem.js",
    "/ViewCode.js": "/ViewCode.js",
    "/ExamViewCode.js": "/ExamViewCode.js",
    "/ProblemStatus.js": "/ProblemStatus.js",
    "/Problem.js": "/Problem.js",
    "/AuthorsRankList.js": "/AuthorsRankList.js",
    "/ExamStatus.js": "/ExamStatus.js",
    "/Exam.js": "/Exam.js",
    "/Status.js": "/Status.js",
    "/Contest.js": "/Contest.js",
    "/UserInformation.js": "/UserInformation.js",
    "/Register.js": "/Register.js",
    "/Modify.js": "/Modify.js",
    "/Home.js": "/Home.js",
    "/Written.js": "/Written.js",
    "/ExamRank.js": "/ExamRank.js",
    "/ExamProblemList.js": "/ExamProblemList.js",
    "/Rank.js": "/Rank.js",
    "/ProblemList.js": "/ProblemList.js",
    "/js/app.js": "/js/app.js",
    "/css/app.css": "/css/app.css"
}